django_xz_queue
