Metadata-Version: 1.1
Name: django-xz-queue
Version: 0.0.1.7
Summary: An Django app that provides django integration for aliyun-mns/redis
Home-page: https://github.com/AoAoStudio/django_xz_queue
Author: xingzhe
Author-email: developer@bi-ci.com
License: MIT
Platform: UNKNOWN
Classifier: Development Status :: 4 - Beta
Classifier: Environment :: Web Environment
Classifier: Framework :: Django
Classifier: Intended Audience :: Developers
Classifier: License :: OSI Approved :: MIT License
Classifier: Operating System :: OS Independent
Classifier: Programming Language :: Python
Classifier: Programming Language :: Python :: 2.7
Classifier: Topic :: Internet :: WWW/HTTP
Classifier: Topic :: Software Development :: Libraries :: Python Modules
